README.md
setup.py
UPL/Core.py
UPL/__init__.py
UPL/gui_impliments.py
UPL/sqlDB.py
UPL/upl_byte.py
UPL/upl_cipher.py
UPL/upl_logger.py
UPL/upl_photoTools.py
UPL/upl_sound.py
UPL/upl_time.py
UPL.egg-info/PKG-INFO
UPL.egg-info/SOURCES.txt
UPL.egg-info/dependency_links.txt
UPL.egg-info/top_level.txt