Metadata-Version: 1.1
Name: UPL
Version: 0.6.1.1
Summary: Universal Python Library
Home-page: https://github.com/RyanD524/UPL
Author: Ryan Draskovics
Author-email: crossroadsact@gmail.com
License: MIT License
Platform: UNKNOWN
Classifier: Development Status :: 6 - Mature
Classifier: License :: Freeware
Classifier: Intended Audience :: Developers
Classifier: Natural Language :: English
Classifier: Programming Language :: Python :: 3
Classifier: Programming Language :: Python :: 3.8
Classifier: Programming Language :: Python :: 3.9
